mypackage/__init__.py
mypackage/__version__.py
mypackage/core.py
concourse_ci_python_project_demo_mike-2.0.dist-info/METADATA
concourse_ci_python_project_demo_mike-2.0.dist-info/WHEEL
concourse_ci_python_project_demo_mike-2.0.dist-info/top_level.txt
concourse_ci_python_project_demo_mike-2.0.dist-info/RECORD
