Metadata-Version: 2.1
Name: concourse-ci-python-project-demo-mike
Version: 2.0
Summary: Concourse CI testing package.
Home-page: https://github.com/timefcuk/sample-python-project.git
Author: timefcuk
Author-email: me@example.com
License: MIT
Platform: UNKNOWN
Classifier: License :: OSI Approved :: MIT License
Classifier: Programming Language :: Python
Classifier: Programming Language :: Python :: 3
Classifier: Programming Language :: Python :: 3.6
Classifier: Programming Language :: Python :: Implementation :: CPython
Classifier: Programming Language :: Python :: Implementation :: PyPy
Requires-Python: >=3.6.0
